.gitignore
EXAMPLE_VENV.sh
LICENSE.md
MANIFEST.in
MANIFEST.in~
NAME
README.md
VERSION
setup.py
datawork/__init__.py
datawork/engine/gather.py
datawork/engine/geo2rdb.py
datawork/engine/signal_geojson.py
datawork/engine/station_codes.py
datawork/engine/.mypy_cache/3.8/@plugins_snapshot.json
datawork/engine/.mypy_cache/3.8/_ast.data.json
datawork/engine/.mypy_cache/3.8/_ast.meta.json
datawork/engine/.mypy_cache/3.8/_importlib_modulespec.data.json
datawork/engine/.mypy_cache/3.8/_importlib_modulespec.meta.json
datawork/engine/.mypy_cache/3.8/_thread.data.json
datawork/engine/.mypy_cache/3.8/_thread.meta.json
datawork/engine/.mypy_cache/3.8/_types.data.json
datawork/engine/.mypy_cache/3.8/_types.meta.json
datawork/engine/.mypy_cache/3.8/abc.data.json
datawork/engine/.mypy_cache/3.8/abc.meta.json
datawork/engine/.mypy_cache/3.8/array.data.json
datawork/engine/.mypy_cache/3.8/array.meta.json
datawork/engine/.mypy_cache/3.8/ast.data.json
datawork/engine/.mypy_cache/3.8/ast.meta.json
datawork/engine/.mypy_cache/3.8/builtins.data.json
datawork/engine/.mypy_cache/3.8/builtins.meta.json
datawork/engine/.mypy_cache/3.8/codecs.data.json
datawork/engine/.mypy_cache/3.8/codecs.meta.json
datawork/engine/.mypy_cache/3.8/contextvars.data.json
datawork/engine/.mypy_cache/3.8/contextvars.meta.json
datawork/engine/.mypy_cache/3.8/datetime.data.json
datawork/engine/.mypy_cache/3.8/datetime.meta.json
datawork/engine/.mypy_cache/3.8/enum.data.json
datawork/engine/.mypy_cache/3.8/enum.meta.json
datawork/engine/.mypy_cache/3.8/genericpath.data.json
datawork/engine/.mypy_cache/3.8/genericpath.meta.json
datawork/engine/.mypy_cache/3.8/io.data.json
datawork/engine/.mypy_cache/3.8/io.meta.json
datawork/engine/.mypy_cache/3.8/mmap.data.json
datawork/engine/.mypy_cache/3.8/mmap.meta.json
datawork/engine/.mypy_cache/3.8/pathlib.data.json
datawork/engine/.mypy_cache/3.8/pathlib.meta.json
datawork/engine/.mypy_cache/3.8/posix.data.json
datawork/engine/.mypy_cache/3.8/posix.meta.json
