Metadata-Version: 2.1
Name: datawork
Version: 1.0.56
Summary: Data Work system gather all data from a database to make analysis and charts
Home-page: http://gitlab.csn.uchile.cl/dpineda/datawork
Author: David Pineda Osorio
Author-email: dpineda@csn.uchile.cl
License: GPLv3
Keywords: collector,gnss,scheduler,async,multiprocess
Platform: UNKNOWN
